sectionproperties_tools/__init__.py
sectionproperties_tools/extraction.py
sectionproperties_tools/serialize.py
sectionproperties_tools-0.3.2.dist-info/licenses/LICENSE
sectionproperties_tools-0.3.2.dist-info/WHEEL
sectionproperties_tools-0.3.2.dist-info/METADATA
sectionproperties_tools-0.3.2.dist-info/RECORD
