Metadata-Version: 2.4
Name: sectionproperties-tools
Version: 0.3.2
Summary: sectionproperties_tools
Author-email: Connor Ferster <connorferster@gmail.com>
Requires-Python: >=3.11
License-File: LICENSE
Requires-Dist: pydantic_core==2.27.2
Requires-Dist: pydantic==2.10.6
Requires-Dist: sectionproperties>=3.9.0
